{
  "type": "object",
  "properties": {
    "url": {
      "type": "string",
      "enum": [
        "https://api-http.littlebitscloud.cc/devices/:device_id",
        "https://api-http.littlebitscloud.cc/devices/:device_id/output",
        "https://api-http.littlebitscloud.cc/subscriptions",
        "https://api-http.littlebitscloud.cc/subscriptions",
        "https://api-http.littlebitscloud.cc/subscriptions"
      ]
    },
    "https://api-http.littlebitscloud.cc/devices/:device_id#:device_id": {
      "type": "string",
      "description": "Device ID",
      "required": true
    },
    "https://api-http.littlebitscloud.cc/devices/:device_id#stealthy_like_a_ninja": {
      "type": "string",
      "description": "You can't see me",
      "required": true
    },
    "https://api-http.littlebitscloud.cc/devices/:device_id/output#:device_id": {
      "type": "string",
      "description": "Device Id",
      "required": true
    },
    "https://api-http.littlebitscloud.cc/devices/:device_id/output#percent": {
      "type": "integer",
      "description": "Percent"
    },
    "https://api-http.littlebitscloud.cc/devices/:device_id/output#duration_ms": {
      "type": "integer",
      "description": "Duration Milliseconds"
    },
    "https://api-http.littlebitscloud.cc/subscriptions#subscriber_id": {
      "type": "string",
      "description": "Subscriber Id"
    },
    "https://api-http.littlebitscloud.cc/subscriptions#publisher_id": {
      "type": "string",
      "description": "Publisher Id"
    },
    "https://api-http.littlebitscloud.cc/subscriptions#publisher_events": {
      "type": "string",
      "description": "Publisher Events"
    }
  }
}